{
  "type": "Feature",
  "geometry": {
    "type": "Point",
    "coordinates": [-5.72183888888889, 54.5323611111111]
  },
  "properties": {
    "address": {
      "street-address": "Ballygraffan Road",
      "locality": "Comber",
      "postal-code": "BT23 5SU"
    },
    "url": "http://www.comberrifleclub.com/"
  }
}
