{
  "type": "Feature",
  "geometry": {
    "type": "Point",
    "coordinates": [-6.25254297679989, 53.3443899108315]
  },
  "properties": {
    "address": {
      "street-address": "c/o DUCAC",
      "extended-address": ["Sports Centre","Trinity College"],
      "locality": "Dublin",
      "postal-code": "2"
    },
    "url": "http://www.rifle.tcdlife.ie/"
  }
}
